smpljson.py
smpljson-0.1.0.dist-info/WHEEL
smpljson-0.1.0.dist-info/METADATA
smpljson-0.1.0.dist-info/RECORD
